Pyplaylist_spotify.py
Pyplaylist_spotify-0.0.1.dist-info/LICENSE.txt
Pyplaylist_spotify-0.0.1.dist-info/METADATA
Pyplaylist_spotify-0.0.1.dist-info/WHEEL
Pyplaylist_spotify-0.0.1.dist-info/top_level.txt
Pyplaylist_spotify-0.0.1.dist-info/RECORD
