Metadata-Version: 2.1
Name: Pyplaylist_spotify
Version: 0.0.1
Summary: It generally creates and trigger a function to add songs into you spotify playlist
Author: Subhendu Adhikari
Keywords: spotify_playlist,playlist_maker,playlist_creater
Classifier: Programming Language :: Python :: 3
Classifier: License :: OSI Approved :: MIT License
Classifier: Operating System :: OS Independent
Requires-Python: >=3.9 
License-File: LICENSE.txt
Requires-Dist: requests
Requires-Dist: beautifulsoup4
